lovense_api/__init__.py
lovense_api/api.py
pylovense/__init__.py
pylovense/api.py
pylovense-0.6.dist-info/LICENSE
pylovense-0.6.dist-info/METADATA
pylovense-0.6.dist-info/WHEEL
pylovense-0.6.dist-info/top_level.txt
pylovense-0.6.dist-info/RECORD
